{ "columns":15,
 "image":"tiles.png",
 "imageheight":320,
 "imagewidth":240,
 "margin":0,
 "name":"tileset",
 "spacing":0,
 "tilecount":300,
 "tiledversion":"1.2.1",
 "tileheight":16,
 "tiles":[
        {
         "id":0,
         "type":"wall"
        }, 
        {
         "id":1,
         "type":"wall"
        }, 
        {
         "id":2,
         "type":"wall"
        }, 
        {
         "id":3,
         "type":"wall"
        }, 
        {
         "id":4,
         "type":"wall"
        }, 
        {
         "id":5,
         "type":"wall"
        }, 
        {
         "id":10,
         "type":"wall"
        }, 
        {
         "id":11,
         "type":"wall"
        }, 
        {
         "id":12,
         "type":"wall"
        }, 
        {
         "id":13,
         "type":"wall"
        }, 
        {
         "id":14,
         "type":"wall"
        }, 
        {
         "id":15,
         "type":"wall"
        }, 
        {
         "id":18,
         "type":"wall"
        }, 
        {
         "id":25,
         "type":"wall"
        }, 
        {
         "id":26,
         "type":"wall"
        }, 
        {
         "id":27,
         "type":"wall"
        }, 
        {
         "id":28,
         "type":"wall"
        }, 
        {
         "id":29,
         "type":"wall"
        }, 
        {
         "id":30,
         "type":"wall"
        }, 
        {
         "id":33,
         "type":"wall"
        }, 
        {
         "id":40,
         "type":"wall"
        }, 
        {
         "id":41,
         "type":"wall"
        }, 
        {
         "id":42,
         "type":"wall"
        }, 
        {
         "id":43,
         "type":"wall"
        }, 
        {
         "id":44,
         "type":"wall"
        }, 
        {
         "id":45,
         "type":"wall"
        }, 
        {
         "id":46,
         "type":"wall"
        }, 
        {
         "id":47,
         "type":"wall"
        }, 
        {
         "id":48,
         "type":"wall"
        }, 
        {
         "id":56,
         "type":"wall"
        }, 
        {
         "id":57,
         "type":"wall"
        }, 
        {
         "id":58,
         "type":"wall"
        }, 
        {
         "id":59,
         "type":"wall"
        }, 
        {
         "id":65,
         "type":"wall"
        }, 
        {
         "id":71,
         "type":"wall"
        }, 
        {
         "id":72,
         "type":"wall"
        }, 
        {
         "id":73,
         "type":"wall"
        }, 
        {
         "id":74,
         "type":"wall"
        }, 
        {
         "id":76,
         "type":"wall"
        }, 
        {
         "id":77,
         "type":"wall"
        }, 
        {
         "id":78,
         "type":"wall"
        }, 
        {
         "id":79,
         "type":"wall"
        }, 
        {
         "id":86,
         "type":"wall"
        }, 
        {
         "id":87,
         "type":"wall"
        }, 
        {
         "id":88,
         "type":"wall"
        }, 
        {
         "id":89,
         "type":"wall"
        }, 
        {
         "id":91,
         "type":"wall"
        }, 
        {
         "id":92,
         "type":"wall"
        }, 
        {
         "id":93,
         "type":"wall"
        }, 
        {
         "id":94,
         "type":"wall"
        }, 
        {
         "id":103,
         "type":"wall"
        }, 
        {
         "id":104,
         "type":"wall"
        }, 
        {
         "id":106,
         "type":"wall"
        }, 
        {
         "id":107,
         "type":"wall"
        }, 
        {
         "id":108,
         "type":"wall"
        }, 
        {
         "id":109,
         "type":"wall"
        }, 
        {
         "id":115,
         "type":"wall"
        }, 
        {
         "id":116,
         "type":"wall"
        }, 
        {
         "id":118,
         "type":"wall"
        }, 
        {
         "id":119,
         "type":"wall"
        }, 
        {
         "id":121,
         "type":"wall"
        }, 
        {
         "id":122,
         "type":"wall"
        }, 
        {
         "id":123,
         "type":"wall"
        }, 
        {
         "id":124,
         "type":"wall"
        }, 
        {
         "id":130,
         "type":"wall"
        }, 
        {
         "id":131,
         "type":"wall"
        }, 
        {
         "id":133,
         "type":"wall"
        }, 
        {
         "id":134,
         "type":"wall"
        }, 
        {
         "id":140,
         "type":"wall"
        }, 
        {
         "id":141,
         "type":"wall"
        }, 
        {
         "id":142,
         "type":"wall"
        }, 
        {
         "id":143,
         "type":"spike"
        }, 
        {
         "id":144,
         "type":"spike"
        }, 
        {
         "id":145,
         "type":"wall"
        }, 
        {
         "id":146,
         "type":"wall"
        }, 
        {
         "id":148,
         "type":"wall"
        }, 
        {
         "id":149,
         "type":"wall"
        }, 
        {
         "id":150,
         "type":"oneway"
        }, 
        {
         "id":151,
         "type":"wall"
        }, 
        {
         "id":152,
         "type":"oneway"
        }, 
        {
         "id":153,
         "type":"oneway"
        }, 
        {
         "id":154,
         "type":"oneway"
        }, 
        {
         "id":155,
         "type":"oneway"
        }, 
        {
         "id":156,
         "type":"oneway"
        }, 
        {
         "id":157,
         "type":"wall"
        }, 
        {
         "id":158,
         "type":"oneway"
        }, 
        {
         "id":160,
         "type":"wall"
        }, 
        {
         "id":161,
         "type":"wall"
        }, 
        {
         "id":162,
         "type":"wall"
        }, 
        {
         "id":163,
         "type":"wall"
        }, 
        {
         "id":164,
         "type":"wall"
        }, 
        {
         "id":166,
         "type":"wall"
        }, 
        {
         "id":172,
         "type":"wall"
        }, 
        {
         "id":175,
         "type":"wall"
        }, 
        {
         "id":176,
         "type":"wall"
        }, 
        {
         "id":177,
         "type":"wall"
        }, 
        {
         "id":178,
         "type":"wall"
        }, 
        {
         "id":179,
         "type":"wall"
        }, 
        {
         "id":181,
         "type":"wall"
        }, 
        {
         "id":182,
         "type":"wall"
        }, 
        {
         "id":183,
         "type":"wall"
        }, 
        {
         "id":185,
         "type":"wall"
        }, 
        {
         "id":186,
         "type":"wall"
        }, 
        {
         "id":187,
         "type":"wall"
        }, 
        {
         "id":189,
         "type":"oneway"
        }, 
        {
         "id":190,
         "type":"oneway"
        }, 
        {
         "id":191,
         "type":"oneway"
        }, 
        {
         "id":192,
         "type":"wall"
        }, 
        {
         "id":193,
         "type":"wall"
        }, 
        {
         "id":194,
         "type":"wall"
        }, 
        {
         "id":195,
         "type":"wall"
        }, 
        {
         "id":196,
         "type":"wall"
        }, 
        {
         "id":197,
         "type":"wall"
        }, 
        {
         "id":201,
         "type":"wall"
        }, 
        {
         "id":202,
         "type":"wall"
        }, 
        {
         "id":203,
         "type":"wall"
        }, 
        {
         "id":205,
         "type":"oneway"
        }, 
        {
         "id":207,
         "type":"wall"
        }, 
        {
         "id":208,
         "type":"wall"
        }, 
        {
         "id":209,
         "type":"wall"
        }, 
        {
         "id":210,
         "type":"wall"
        }, 
        {
         "id":211,
         "type":"wall"
        }, 
        {
         "id":212,
         "type":"wall"
        }, 
        {
         "id":216,
         "type":"wall"
        }, 
        {
         "id":217,
         "type":"wall"
        }, 
        {
         "id":218,
         "type":"wall"
        }, 
        {
         "id":219,
         "type":"wall"
        }, 
        {
         "id":222,
         "type":"wall"
        }, 
        {
         "id":223,
         "type":"wall"
        }, 
        {
         "id":224,
         "type":"wall"
        }, 
        {
         "id":225,
         "type":"wall"
        }, 
        {
         "id":226,
         "type":"wall"
        }, 
        {
         "id":227,
         "type":"wall"
        }, 
        {
         "id":228,
         "type":"wall"
        }, 
        {
         "id":229,
         "type":"wall"
        }, 
        {
         "id":230,
         "type":"wall"
        }, 
        {
         "id":231,
         "type":"wall"
        }, 
        {
         "id":234,
         "type":"wall"
        }, 
        {
         "id":236,
         "type":"wall"
        }, 
        {
         "id":237,
         "type":"wall"
        }, 
        {
         "id":238,
         "type":"wall"
        }, 
        {
         "id":239,
         "type":"wall"
        }, 
        {
         "id":240,
         "type":"wall"
        }, 
        {
         "id":241,
         "type":"wall"
        }, 
        {
         "id":242,
         "type":"wall"
        }, 
        {
         "id":243,
         "type":"wall"
        }, 
        {
         "id":244,
         "type":"wall"
        }, 
        {
         "id":245,
         "type":"wall"
        }, 
        {
         "id":246,
         "type":"wall"
        }, 
        {
         "id":247,
         "type":"wall"
        }, 
        {
         "id":248,
         "type":"wall"
        }, 
        {
         "id":249,
         "type":"wall"
        }, 
        {
         "id":251,
         "type":"wall"
        }, 
        {
         "id":252,
         "type":"wall"
        }, 
        {
         "id":253,
         "type":"wall"
        }, 
        {
         "id":254,
         "type":"wall"
        }, 
        {
         "id":255,
         "type":"wall"
        }, 
        {
         "id":256,
         "type":"wall"
        }, 
        {
         "id":257,
         "type":"wall"
        }, 
        {
         "id":258,
         "type":"wall"
        }, 
        {
         "id":259,
         "type":"wall"
        }, 
        {
         "id":260,
         "type":"wall"
        }, 
        {
         "id":261,
         "type":"wall"
        }, 
        {
         "id":262,
         "type":"wall"
        }, 
        {
         "id":263,
         "type":"wall"
        }, 
        {
         "id":266,
         "type":"wall"
        }, 
        {
         "id":267,
         "type":"wall"
        }, 
        {
         "id":268,
         "type":"wall"
        }, 
        {
         "id":275,
         "type":"wall"
        }, 
        {
         "id":276,
         "type":"wall"
        }, 
        {
         "id":277,
         "type":"wall"
        }, 
        {
         "id":278,
         "type":"wall"
        }, 
        {
         "id":280,
         "type":"wall"
        }, 
        {
         "id":281,
         "type":"wall"
        }, 
        {
         "id":282,
         "type":"wall"
        }, 
        {
         "id":283,
         "type":"wall"
        }, 
        {
         "id":285,
         "type":"startpos"
        }, 
        {
         "id":286,
         "type":"breakable"
        }, 
        {
         "id":287,
         "type":"altarjetpack"
        }, 
        {
         "id":288,
         "type":"altarshield"
        }, 
        {
         "id":289,
         "type":"altargun"
        }, 
        {
         "id":290,
         "type":"gem"
        }, 
        {
         "id":291,
         "type":"rocket"
        }, 
        {
         "id":293,
         "type":"wall"
        }, 
        {
         "id":296,
         "type":"wall"
        }, 
        {
         "id":297,
         "type":"wall"
        }, 
        {
         "id":298,
         "type":"wall"
        }],
 "tilewidth":16,
 "transparentcolor":"#000000",
 "type":"tileset",
 "version":1.2
}